pydantic_settings_helper/__init__.py
pydantic_settings_helper-0.2.0.dist-info/METADATA
pydantic_settings_helper-0.2.0.dist-info/WHEEL
pydantic_settings_helper-0.2.0.dist-info/entry_points.txt
pydantic_settings_helper-0.2.0.dist-info/licenses/LICENSE
pydantic_settings_helper-0.2.0.dist-info/RECORD
