Metadata-Version: 2.4
Name: pydantic-settings-helper
Version: 0.2.0
Summary: Add your description here
Author-email: Sygmei <3835355+Sygmei@users.noreply.github.com>
License-File: LICENSE
Requires-Python: >=3.12
Requires-Dist: pydantic-settings>=2.9.1
Requires-Dist: pydantic>=2.11.3
